Metadata-Version: 2.1
Name: depix
Version: 1.0.2
Summary: Depix is a tool for recovering passwords from pixelized screenshots.
Home-page: https://github.com/beurtschipper/Depix
Author: beurtschipper
License: CC BY 4.0
Platform: UNKNOWN
Classifier: Programming Language :: Python
